{
	"credit": "Made with Blockbench",
	"parent": "block/block",
	"textures": {
		"0": "tfmg:block/glass_insulator",
		"particle": "tfmg:block/glass_insulator"
	},
	"elements": [
		{
			"from": [4, 7, 4],
			"to": [12, 9, 12],
			"rotation": {"angle": 0, "axis": "y", "origin": [6, 7, 9]},
			"faces": {
				"north": {"uv": [8, 0, 0, 2], "texture": "#0"},
				"east": {"uv": [8, 0, 0, 2], "texture": "#0"},
				"south": {"uv": [0, 0, 8, 2], "texture": "#0"},
				"west": {"uv": [0, 0, 8, 2], "texture": "#0"},
				"up": {"uv": [0, 0, 8, 8], "texture": "#0"},
				"down": {"uv": [0, 0, 8, 8], "texture": "#0"}
			}
		},
		{
			"from": [6, 6, 6],
			"to": [10, 7, 10],
			"rotation": {"angle": 0, "axis": "y", "origin": [7, 6, 7]},
			"faces": {
				"north": {"uv": [7, 10, 11, 11], "texture": "#0"},
				"east": {"uv": [7, 10, 11, 11], "texture": "#0"},
				"south": {"uv": [7, 11, 11, 12], "texture": "#0"},
				"west": {"uv": [7, 10, 11, 11], "texture": "#0"},
				"up": {"uv": [7, 10, 11, 14], "texture": "#0"},
				"down": {"uv": [7, 10, 11, 14], "texture": "#0"}
			}
		},
		{
			"from": [6, 9, 6],
			"to": [10, 10, 10],
			"rotation": {"angle": 0, "axis": "y", "origin": [7, 9, 7]},
			"faces": {
				"north": {"uv": [7, 11, 11, 12], "texture": "#0"},
				"east": {"uv": [7, 11, 11, 12], "texture": "#0"},
				"south": {"uv": [7, 12, 11, 13], "texture": "#0"},
				"west": {"uv": [7, 11, 11, 12], "texture": "#0"},
				"up": {"uv": [7, 10, 11, 14], "texture": "#0"},
				"down": {"uv": [7, 10, 11, 14], "texture": "#0"}
			}
		}
	]
}